cpak/__init__.py
cpak-0.0.1.dist-info/LICENSE
cpak-0.0.1.dist-info/METADATA
cpak-0.0.1.dist-info/WHEEL
cpak-0.0.1.dist-info/top_level.txt
cpak-0.0.1.dist-info/RECORD
