Metadata-Version: 2.1
Name: cpak
Version: 0.0.1
Summary: A package manager and build system for c/c++ using python
Home-page: https://github.com/yhl1219/cpak
Author: yhl1219
Author-email: yhliu2000@outlook.com
License: UNKNOWN
Project-URL: Bug Tracker, https://github.com/yhl1219/cpak/issues
Platform: UNKNOWN
Classifier: Programming Language :: Python :: 3
Classifier: License :: OSI Approved :: MIT License
Classifier: Operating System :: OS Independent
Requires-Python: >=3.6
License-File: LICENSE
